HISTORY.rst
LICENSE
MANIFEST.in
NOTICE
README.rst
setup.cfg
setup.py
robobrowser/__init__.py
robobrowser/browser.py
robobrowser/cache.py
robobrowser/compat.py
robobrowser/exceptions.py
robobrowser/helpers.py
robobrowser/ordereddict.py
robobrowser/responses.py
robobrowser/forms/__init__.py
robobrowser/forms/fields.py
robobrowser/forms/form.py
robobrowserdash.egg-info/PKG-INFO
robobrowserdash.egg-info/SOURCES.txt
robobrowserdash.egg-info/dependency_links.txt
robobrowserdash.egg-info/not-zip-safe
robobrowserdash.egg-info/requires.txt
robobrowserdash.egg-info/top_level.txt